cdklabs/cdk_aws_sagemaker_role_manager/__init__.py
cdklabs/cdk_aws_sagemaker_role_manager/py.typed
cdklabs/cdk_aws_sagemaker_role_manager/_jsii/__init__.py
cdklabs/cdk_aws_sagemaker_role_manager/_jsii/cdk-aws-sagemaker-role-manager@0.0.30.jsii.tgz
cdklabs.cdk_aws_sagemaker_role_manager-0.0.30.dist-info/LICENSE
cdklabs.cdk_aws_sagemaker_role_manager-0.0.30.dist-info/METADATA
cdklabs.cdk_aws_sagemaker_role_manager-0.0.30.dist-info/NOTICE
cdklabs.cdk_aws_sagemaker_role_manager-0.0.30.dist-info/WHEEL
cdklabs.cdk_aws_sagemaker_role_manager-0.0.30.dist-info/top_level.txt
cdklabs.cdk_aws_sagemaker_role_manager-0.0.30.dist-info/RECORD
